<?xml version="1.0"?>
<Root>
	<Entry>
		<zType>IMPROVEMENT_ANCIENT_RUINS</zType>
		<aiBonusDie>
			<Pair>
				<zIndex>BONUS_REVEAL_MAP</zIndex>
				<iValue>1</iValue>
			</Pair>
			<Pair>
				<zIndex>BONUS_YIELD_CIVICS</zIndex>
				<iValue>1</iValue>
			</Pair>
			<Pair>
				<zIndex>BONUS_YIELD_TRAINING</zIndex>
				<iValue>1</iValue>
			</Pair>
			<Pair>
				<zIndex>BONUS_YIELD_MONEY</zIndex>
				<iValue>1</iValue>
			</Pair>
			<Pair>
				<zIndex>BONUS_YIELD_ORDERS</zIndex>
				<iValue>1</iValue>
			</Pair>
			<Pair>
				<zIndex>BONUS_YIELD_FOOD</zIndex>
				<iValue>1</iValue>
			</Pair>
			<Pair>
				<zIndex>BONUS_YIELD_WOOD</zIndex>
				<iValue>1</iValue>
			</Pair>
			<Pair>
				<zIndex>BONUS_YIELD_STONE</zIndex>
				<iValue>1</iValue>
			</Pair>
			<Pair>
				<zIndex>BONUS_YIELD_IRON</zIndex>
				<iValue>1</iValue>
			</Pair>
			<Pair>
				<zIndex>BONUS_UNIT_SCOUT</zIndex>
				<iValue>1</iValue>
			</Pair>
			<Pair>	<!-- instead of Bonus Techs -->
				<zIndex>BONUS_YIELD_SCIENCE</zIndex>
				<iValue>1</iValue>
			</Pair>
		</aiBonusDie>
	</Entry>
	<Entry>
		<zType>IMPROVEMENT_SETTLEMENT_1</zType>
		<Class>IMPROVEMENTCLASS_SETTLEMENT</Class>
	</Entry>
	<Entry>
		<zType>IMPROVEMENT_SETTLEMENT_2</zType>
		<Class>IMPROVEMENTCLASS_SETTLEMENT</Class>
	</Entry>
	<Entry>
		<zType>IMPROVEMENT_SETTLEMENT_3</zType>
		<Class>IMPROVEMENTCLASS_SETTLEMENT</Class>
	</Entry>
	<Entry>
		<zType>IMPROVEMENT_SETTLEMENT_4</zType>
		<Class>IMPROVEMENTCLASS_SETTLEMENT</Class>
	</Entry>
	<Entry>   <!-- disable Forts for 1.0.64196+ -->
		<zType>IMPROVEMENT_FORT</zType>
		<bBuild>0</bBuild>
	</Entry>
	<Entry>
		<zType>IMPROVEMENT_THEATER_2</zType>
		<iSpecialistCost>-15</iSpecialistCost>
		<Specialist>SPECIALIST_POET_1</Specialist>
	</Entry>
	<Entry>
		<zType>IMPROVEMENT_THEATER_3</zType>
		<iSpecialistCost>-30</iSpecialistCost>
		<Specialist>SPECIALIST_POET_1</Specialist>
	</Entry>
	<Entry>
		<zType>IMPROVEMENT_BATHS_1</zType>
		<bRequiresUrban>0</bRequiresUrban>
		<UpgradeImprovement></UpgradeImprovement>
		<Specialist>SPECIALIST_DOCTOR_1</Specialist>
		<aiYieldCost>
			<Pair>
				<zIndex>YIELD_STONE</zIndex>
				<iValue>50</iValue>
			</Pair>
		</aiYieldCost>
		<aiYieldOutput>
			<Pair>
				<zIndex>YIELD_HAPPINESS</zIndex>
				<iValue>40</iValue>
			</Pair>
		</aiYieldOutput>
		<aiYieldConsumption>
			<Pair>
				<zIndex>YIELD_STONE</zIndex>
				<iValue>-40</iValue>
			</Pair>
		</aiYieldConsumption>
		<aiYieldPillage>
			<Pair>
				<zIndex>YIELD_STONE</zIndex>
				<iValue>25</iValue>
			</Pair>
		</aiYieldPillage>
		<CityBiomePrereq>BIOME_HOT</CityBiomePrereq>
	</Entry>
	<Entry>
		<zType>IMPROVEMENT_BATHS_2</zType>
		<iSpecialistCost>0</iSpecialistCost>
		<bRequiresUrban>0</bRequiresUrban>
		<CulturePrereq>CULTURE_DEVELOPING</CulturePrereq>
		<ImprovementPrereq></ImprovementPrereq>
		<UpgradeImprovement></UpgradeImprovement>
		<Specialist>SPECIALIST_DOCTOR_1</Specialist>
		<aiYieldCost>
			<Pair>
				<zIndex>YIELD_STONE</zIndex>
				<iValue>40</iValue>
			</Pair>
		</aiYieldCost>
		<aiYieldOutput>
			<Pair>
				<zIndex>YIELD_HAPPINESS</zIndex>
				<iValue>30</iValue>
			</Pair>
		</aiYieldOutput>
		<aiYieldConsumption>
			<Pair>
				<zIndex>YIELD_STONE</zIndex>
				<iValue>-30</iValue>
			</Pair>
		</aiYieldConsumption>
		<aiYieldPillage>
			<Pair>
				<zIndex>YIELD_STONE</zIndex>
				<iValue>20</iValue>
			</Pair>
		</aiYieldPillage>
		<CityBiomePrereq>BIOME_TEMPERATE</CityBiomePrereq>
	</Entry>
	<Entry>
		<zType>IMPROVEMENT_BATHS_3</zType>
		<iSpecialistCost>0</iSpecialistCost>
		<bRequiresUrban>0</bRequiresUrban>
		<CulturePrereq>CULTURE_DEVELOPING</CulturePrereq>
		<ImprovementPrereq></ImprovementPrereq>
		<EffectCity>EFFECTCITY_IMPROVEMENT_BATHS_3</EffectCity>
		<Specialist>SPECIALIST_DOCTOR_1</Specialist>
		<aiYieldCost>
			<Pair>
				<zIndex>YIELD_STONE</zIndex>
				<iValue>80</iValue>
			</Pair>
		</aiYieldCost>
		<aiYieldOutput>
			<Pair>
				<zIndex>YIELD_HAPPINESS</zIndex>
				<iValue>40</iValue>
			</Pair>
		</aiYieldOutput>
		<aiYieldConsumption>
			<Pair>
				<zIndex>YIELD_WOOD</zIndex>
				<iValue>-60</iValue>
			</Pair>
		</aiYieldConsumption>
		<aiYieldPillage>
			<Pair>
				<zIndex>YIELD_STONE</zIndex>
				<iValue>40</iValue>
			</Pair>
		</aiYieldPillage>
		<CityBiomePrereq>BIOME_COLD</CityBiomePrereq>
	</Entry>
	<Entry>
		<zType>IMPROVEMENT_MARKET_1</zType>
		<SecondaryUnlockTechPrereq>TECH_NAVIGATION</SecondaryUnlockTechPrereq>
		<SecondaryUnlockCulturePrereq>CULTURE_STRONG</SecondaryUnlockCulturePrereq>
		<TertiaryUnlockFamilyClassPrereq>FAMILYCLASS_TRADERS</TertiaryUnlockFamilyClassPrereq>
		<TertiaryUnlockTechPrereq>TECH_POLIS</TertiaryUnlockTechPrereq>
		<TertiaryUnlockCulturePrereq>CULTURE_DEVELOPING</TertiaryUnlockCulturePrereq>
	</Entry>
	<Entry>
		<zType>IMPROVEMENT_MARKET_2</zType>
		<iSpecialistCost>-15</iSpecialistCost>
		<Specialist>SPECIALIST_SHOPKEEPER_1</Specialist>
		<TertiaryUnlockFamilyClassPrereq>FAMILYCLASS_TRADERS</TertiaryUnlockFamilyClassPrereq>
		<TertiaryUnlockTechPrereq>TECH_NAVIGATION</TertiaryUnlockTechPrereq>
		<TertiaryUnlockCulturePrereq>CULTURE_STRONG</TertiaryUnlockCulturePrereq>
	</Entry>
	<Entry>
		<zType>IMPROVEMENT_MARKET_3</zType>
		<iSpecialistCost>-30</iSpecialistCost>
		<Specialist>SPECIALIST_SHOPKEEPER_1</Specialist>
	</Entry>
	<Entry>
		<zType>IMPROVEMENT_LIBRARY_1</zType>
		<SecondaryUnlockTechPrereq>TECH_CITIZENSHIP</SecondaryUnlockTechPrereq>
		<SecondaryUnlockCulturePrereq>CULTURE_STRONG</SecondaryUnlockCulturePrereq>
		<iSecondaryUnlockPopulationPrereq>5</iSecondaryUnlockPopulationPrereq>
	</Entry>
	<Entry>
		<zType>IMPROVEMENT_LIBRARY_2</zType>
		<iSpecialistCost>-15</iSpecialistCost>
		<Specialist>SPECIALIST_PHILOSOPHER_1</Specialist>
	</Entry>
	<Entry>
		<zType>IMPROVEMENT_LIBRARY_3</zType>
		<iSpecialistCost>-30</iSpecialistCost>
		<Specialist>SPECIALIST_PHILOSOPHER_1</Specialist>
	</Entry>
	<Entry>
		<zType>IMPROVEMENT_COURTHOUSE_1</zType>
		<SecondaryUnlockTechPrereq>TECH_PHALANX</SecondaryUnlockTechPrereq>
		<SecondaryUnlockCulturePrereq>CULTURE_STRONG</SecondaryUnlockCulturePrereq>
		<iSecondaryUnlockPopulationPrereq>5</iSecondaryUnlockPopulationPrereq>
	</Entry>
	<Entry>
		<zType>IMPROVEMENT_COURTHOUSE_2</zType>
		<iSpecialistCost>-15</iSpecialistCost>
		<AdjacentImprovementClassPrereq></AdjacentImprovementClassPrereq>
		<Specialist>SPECIALIST_SCRIBE_1</Specialist>
	</Entry>
	<Entry>
		<zType>IMPROVEMENT_COURTHOUSE_3</zType>
		<iSpecialistCost>-30</iSpecialistCost>
		<Specialist>SPECIALIST_SCRIBE_1</Specialist>
	</Entry>
	<Entry>
		<zType>IMPROVEMENT_APADANA</zType>
		<EffectCity>EFFECTCITY_IMPROVEMENT_APADANA_ALL</EffectCity>
		<EffectPlayer></EffectPlayer>
	</Entry>
	<Entry>
		<zType>IMPROVEMENT_YAZILIKAYA</zType>
		<bHolyCityValid>0</bHolyCityValid>
		<EffectCityPrereq>EFFECTCITY_HOLY_CITY</EffectCityPrereq>
	</Entry>
	<Entry>
		<zType>IMPROVEMENT_LIGHTHOUSE</zType>
		<EffectCity>EFFECTCITY_IMPROVEMENT_LIGHTHOUSE</EffectCity>
	</Entry>
	<Entry>
		<zType>IMPROVEMENT_COLOSSEUM</zType>
		<iUnitTurns>0</iUnitTurns>
		<EffectPlayer>EFFECTPLAYER_IMPROVEMENT_COLOSSEUM</EffectPlayer>
		<aiUnitDie></aiUnitDie>
	</Entry>
	<Entry>
		<zType>IMPROVEMENT_COTHON</zType>
		<iUnitTurns>0</iUnitTurns>
		<aiUnitDie></aiUnitDie>
	</Entry>
	<Entry>
		<zType>IMPROVEMENT_JERWAN_AQUEDUCT</zType>
		<AdjacentImprovementSpecialist></AdjacentImprovementSpecialist>
		<BonusAdjacentImprovementClass>IMPROVEMENTCLASS_BATHS</BonusAdjacentImprovementClass>
		<bMakesAdjacentPassableLandTileValidForBonusImprovement>1</bMakesAdjacentPassableLandTileValidForBonusImprovement>
	</Entry>
<!-- what to do with those -->

	<Entry>
		<zType>IMPROVEMENT_AL_KHAZNEH</zType>
		<Bonus>BONUS_IMPROVEMENT_AL_KHAZNEH</Bonus>
	</Entry>
<!-- 
	<Entry>
		<zType>IMPROVEMENT_HAGIA_SOPHIA</zType>

		<EffectPlayer>EFFECTPLAYER_IMPROVEMENT_HAGIA_SOPHIA</EffectPlayer>
		<EffectCity>EFFECTCITY_IMPROVEMENT_HAGIA_SOPHIA</EffectCity>
		<BonusCities>BONUS_IMPROVEMENT_HAGIA_SOPHIA</BonusCities>

	</Entry>
 -->
<!-- 
	<Entry>
		<zType>IMPROVEMENT_VIA_RECTA_SOUK</zType>
		<EffectCity>EFFECTCITY_IMPROVEMENT_VIA_RECTA_SOUK</EffectCity>
	</Entry>
 -->
	<Entry>
		<zType>IMPROVEMENT_HARBOR</zType>
		<TertiaryUnlockFamilyClassPrereq>FAMILYCLASS_TRADERS</TertiaryUnlockFamilyClassPrereq>
		<TertiaryUnlockTechPrereq>TECH_NAVIGATION</TertiaryUnlockTechPrereq>
		<TertiaryUnlockCulturePrereq>CULTURE_DEVELOPING</TertiaryUnlockCulturePrereq>
	</Entry>
	<Entry>
		<zType>IMPROVEMENT_MONASTERY_ZOROASTRIANISM</zType>
		<TertiaryUnlockFamilyClassPrereq>FAMILYCLASS_CLERICS</TertiaryUnlockFamilyClassPrereq>
		<TertiaryUnlockTechPrereq>TECH_DIVINATION</TertiaryUnlockTechPrereq>
		<TertiaryUnlockEffectCityPrereq>EFFECTCITY_RELIGION_ZOROASTRIANISM_STATE</TertiaryUnlockEffectCityPrereq>
	</Entry>
	<Entry>
		<zType>IMPROVEMENT_MONASTERY_JUDAISM</zType>
		<TertiaryUnlockFamilyClassPrereq>FAMILYCLASS_CLERICS</TertiaryUnlockFamilyClassPrereq>
		<TertiaryUnlockTechPrereq>TECH_DIVINATION</TertiaryUnlockTechPrereq>
		<TertiaryUnlockEffectCityPrereq>EFFECTCITY_RELIGION_JUDAISM_STATE</TertiaryUnlockEffectCityPrereq>
	</Entry>
	<Entry>
		<zType>IMPROVEMENT_MONASTERY_CHRISTIANITY</zType>
		<TertiaryUnlockFamilyClassPrereq>FAMILYCLASS_CLERICS</TertiaryUnlockFamilyClassPrereq>
		<TertiaryUnlockTechPrereq>TECH_DIVINATION</TertiaryUnlockTechPrereq>
		<TertiaryUnlockEffectCityPrereq>EFFECTCITY_RELIGION_CHRISTIANITY_STATE</TertiaryUnlockEffectCityPrereq>
	</Entry>
	<Entry>
		<zType>IMPROVEMENT_MONASTERY_MANICHAEISM</zType>
		<TertiaryUnlockFamilyClassPrereq>FAMILYCLASS_CLERICS</TertiaryUnlockFamilyClassPrereq>
		<TertiaryUnlockTechPrereq>TECH_DIVINATION</TertiaryUnlockTechPrereq>
		<TertiaryUnlockEffectCityPrereq>EFFECTCITY_RELIGION_MANICHAEISM_STATE</TertiaryUnlockEffectCityPrereq>
	</Entry>
	<Entry>
		<zType>IMPROVEMENT_TEMPLE_ZOROASTRIANISM</zType>
		<TertiaryUnlockFamilyClassPrereq>FAMILYCLASS_CLERICS</TertiaryUnlockFamilyClassPrereq>
		<TertiaryUnlockTechPrereq>TECH_METAPHYSICS</TertiaryUnlockTechPrereq>
		<TertiaryUnlockCulturePrereq>CULTURE_STRONG</TertiaryUnlockCulturePrereq>
		<TertiaryUnlockEffectCityPrereq>EFFECTCITY_RELIGION_ZOROASTRIANISM_STATE</TertiaryUnlockEffectCityPrereq>
	</Entry>
	<Entry>
		<zType>IMPROVEMENT_TEMPLE_JUDAISM</zType>
		<TertiaryUnlockFamilyClassPrereq>FAMILYCLASS_CLERICS</TertiaryUnlockFamilyClassPrereq>
		<TertiaryUnlockTechPrereq>TECH_METAPHYSICS</TertiaryUnlockTechPrereq>
		<TertiaryUnlockCulturePrereq>CULTURE_STRONG</TertiaryUnlockCulturePrereq>
		<TertiaryUnlockEffectCityPrereq>EFFECTCITY_RELIGION_JUDAISM_STATE</TertiaryUnlockEffectCityPrereq>
	</Entry>
	<Entry>
		<zType>IMPROVEMENT_TEMPLE_CHRISTIANITY</zType>
		<TertiaryUnlockFamilyClassPrereq>FAMILYCLASS_CLERICS</TertiaryUnlockFamilyClassPrereq>
		<TertiaryUnlockTechPrereq>TECH_METAPHYSICS</TertiaryUnlockTechPrereq>
		<TertiaryUnlockCulturePrereq>CULTURE_STRONG</TertiaryUnlockCulturePrereq>
		<TertiaryUnlockEffectCityPrereq>EFFECTCITY_RELIGION_CHRISTIANITY_STATE</TertiaryUnlockEffectCityPrereq>
	</Entry>
	<Entry>
		<zType>IMPROVEMENT_TEMPLE_MANICHAEISM</zType>
		<TertiaryUnlockFamilyClassPrereq>FAMILYCLASS_CLERICS</TertiaryUnlockFamilyClassPrereq>
		<TertiaryUnlockTechPrereq>TECH_METAPHYSICS</TertiaryUnlockTechPrereq>
		<TertiaryUnlockCulturePrereq>CULTURE_STRONG</TertiaryUnlockCulturePrereq>
		<TertiaryUnlockEffectCityPrereq>EFFECTCITY_RELIGION_MANICHAEISM_STATE</TertiaryUnlockEffectCityPrereq>
	</Entry>
	<Entry>
		<zType>IMPROVEMENT_PAGAN_STATUE_TEMPLE</zType>
		<aiYieldOutput>
			<Pair>
				<zIndex>YIELD_CULTURE</zIndex>
				<iValue>20</iValue>
			</Pair>
		</aiYieldOutput>
	</Entry>
	<Entry>
		<zType>IMPROVEMENT_AMAZON_CULT</zType>
		<aiYieldOutput>
			<Pair>
				<zIndex>YIELD_ORDERS</zIndex>
				<iValue>10</iValue>
			</Pair>
		</aiYieldOutput>
	</Entry>
	<Entry>
		<zType>IMPROVEMENT_MARTYR_CULT</zType>
		<aiYieldOutput>
			<Pair>
				<zIndex>YIELD_MONEY</zIndex>
				<iValue>120</iValue>
			</Pair>
			<Pair>
				<zIndex>YIELD_CULTURE</zIndex>
				<iValue>20</iValue>
			</Pair>
		</aiYieldOutput>
	</Entry>
	<Entry>
		<zType>IMPROVEMENT_DUAL_CULT</zType>
		<aiYieldOutput>
			<Pair>
				<zIndex>YIELD_CIVICS</zIndex>
				<iValue>30</iValue>
			</Pair>
		</aiYieldOutput>
	</Entry>
	<Entry>
		<zType>IMPROVEMENT_CULT_OF_THE_ANGELIC_DIVINE</zType>
		<aiYieldOutput>
			<Pair>
				<zIndex>YIELD_CULTURE</zIndex>
				<iValue>20</iValue>
			</Pair>
			<Pair>
				<zIndex>YIELD_SCIENCE</zIndex>
				<iValue>10</iValue>
			</Pair>
		</aiYieldOutput>
	</Entry>
	<Entry>
		<zType>IMPROVEMENT_CULT_OF_THE_MOTHER</zType>
		<aiYieldOutput>
			<Pair>
				<zIndex>YIELD_CULTURE</zIndex>
				<iValue>20</iValue>
			</Pair>
		</aiYieldOutput>
	</Entry>
	<Entry>
		<zType>IMPROVEMENT_CULT_OF_ISIS_AND_SERAPIS</zType>
		<EffectCity />
		<aiYieldOutput>
			<Pair>
				<zIndex>YIELD_CULTURE</zIndex>
				<iValue>20</iValue>
			</Pair>
			<Pair>
				<zIndex>YIELD_CIVICS</zIndex>
				<iValue>20</iValue>
			</Pair>
		</aiYieldOutput>
	</Entry>
	<Entry>
		<zType>IMPROVEMENT_CULT_OF_MITHRAS</zType>
		<EffectCity>EFFECTCITY_IMPROVEMENT_CULT_OF_MITHRAS</EffectCity>
		<aiYieldOutput>
			<Pair>
				<zIndex>YIELD_TRAINING</zIndex>
				<iValue>20</iValue>
			</Pair>
		</aiYieldOutput>
	</Entry>
</Root>
